personalfinance/__init__.py
personalfinance/cashflow_controller.py
personalfinance/cashflow_model.py
personalfinance/excel_model.py
personalfinance/helpers.py
personalfinance-1.0.0.dist-info/LICENSE
personalfinance-1.0.0.dist-info/METADATA
personalfinance-1.0.0.dist-info/WHEEL
personalfinance-1.0.0.dist-info/RECORD
