Metadata-Version: 2.1
Name: personalfinance
Version: 1.0.0
Summary: Tracking your Income and Expenses Automatically
Home-page: https://www.jeroenbouma.com/projects/personalfinance
License: MIT
Author: Jeroen Bouma
Requires-Python: >=3.10,<3.13
Classifier: Development Status :: 5 - Production/Stable
Classifier: Intended Audience :: Financial and Insurance Industry
Classifier: License :: OSI Approved :: MIT License
Classifier: Operating System :: OS Independent
Classifier: Programming Language :: Python :: 3
Classifier: Programming Language :: Python :: 3.10
Classifier: Programming Language :: Python :: 3.11
Classifier: Programming Language :: Python :: 3.12
Classifier: Topic :: Office/Business :: Financial :: Investment
Requires-Dist: fuzzywuzzy (>=0.18.0,<0.19.0)
Requires-Dist: pandas[excel,performance] (>=2.1.0,<3.0.0)
Requires-Dist: python-levenshtein (>=0.23.0,<0.24.0)
Requires-Dist: requests (>=2.31.0,<3.0.0)
Requires-Dist: tqdm (>=4.66.1,<5.0.0)
Requires-Dist: xlsxwriter (>=3.1.5,<4.0.0)
Project-URL: Repository, https://github.com/JerBouma/PersonalFinance
